tikatree/__init__.py
tikatree/tikatree.py
tikatree-0.1.1.dist-info/LICENSE
tikatree-0.1.1.dist-info/METADATA
tikatree-0.1.1.dist-info/WHEEL
tikatree-0.1.1.dist-info/entry_points.txt
tikatree-0.1.1.dist-info/top_level.txt
tikatree-0.1.1.dist-info/RECORD
