Metadata-Version: 2.1
Name: tikatree
Version: 0.1.1
Summary: Directory tree metadata parser using Apache Tika
Home-page: https://phabricator.kairohm.dev/diffusion/49/
Author: Zeigren
Author-email: zeigren@zeigren.com
License: UNKNOWN
Project-URL: Project Page, https://phabricator.kairohm.dev/project/view/51/
Platform: UNKNOWN
Classifier: Programming Language :: Python :: 3
Classifier: License :: OSI Approved :: MIT License
Classifier: Operating System :: OS Independent
Classifier: Environment :: Console
Classifier: Topic :: Utilities
Requires-Python: >=3.7
Requires-Dist: tika (==1.24)
Requires-Dist: tqdm (==4.50)
Requires-Dist: psutil (==5.7.2)
